deepsnap/__init__.py
deepsnap/batch.py
deepsnap/dataset.py
deepsnap/graph.py
deepsnap/hetero_gnn.py
deepsnap/hetero_graph.py
tests/__init__.py
tests/test_batch.py
tests/test_dataset.py
tests/test_dataset_tensor_backend.py
tests/test_graph.py
tests/test_graph_backend.py
tests/test_graph_tensor_backend.py
tests/test_hetero_graph.py
tests/test_hetero_graph_tensor_backend.py
tests/utils.py
deepsnap-0.2.0.dist-info/LICENSE
deepsnap-0.2.0.dist-info/METADATA
deepsnap-0.2.0.dist-info/WHEEL
deepsnap-0.2.0.dist-info/top_level.txt
deepsnap-0.2.0.dist-info/RECORD
