Metadata-Version: 2.1
Name: deepsnap
Version: 0.2.0
Summary: Deepsnap package
Home-page: https://github.com/snap-stanford/deepsnap
Author: Jiaxuan You*, Rex Ying*, Xinwei He, Zecheng Zhang
Author-email: jiaxuan@cs.stanford.edu, rexy@cs.stanford.edu, xhe17@cs.stanford.edu, zecheng@cs.stanford.edu
License: UNKNOWN
Platform: UNKNOWN
Classifier: Programming Language :: Python :: 3
Classifier: License :: OSI Approved :: MIT License
Classifier: Operating System :: OS Independent
Requires-Python: >=3.6
Requires-Dist: torch
Requires-Dist: networkx
Requires-Dist: numpy
